{
    "AX": {
        "error": 0.00415563987886037, 
        "filter_outliers": true, 
        "filter_outliers_dict": {
            "filter_outliers": true, 
            "iterations": 1, 
            "std_devs": 2
        }, 
        "fit": "Average", 
        "fn": 116, 
        "include_baseline_error": false, 
        "iterations": 1, 
        "n": 120, 
        "std_devs": 2, 
        "value": -0.015737647132670552
    }, 
    "CDD": {
        "error": 7.5068016889568915e-06, 
        "filter_outliers": true, 
        "filter_outliers_dict": {
            "filter_outliers": true, 
            "iterations": 1, 
            "std_devs": 10
        }, 
        "fit": "Average", 
        "fn": 120, 
        "include_baseline_error": false, 
        "iterations": 1, 
        "n": 120, 
        "std_devs": 10, 
        "value": 4.9381249967458035e-05
    }, 
    "H1": {
        "error": 0.0035319117634011214, 
        "filter_outliers": true, 
        "filter_outliers_dict": {
            "filter_outliers": true, 
            "iterations": 1, 
            "std_devs": 2
        }, 
        "fit": "Average", 
        "fn": 113, 
        "include_baseline_error": false, 
        "iterations": 1, 
        "n": 120, 
        "std_devs": 2, 
        "value": -0.024129814807267908
    }, 
    "H2": {
        "error": 0.004946990492623046, 
        "filter_outliers": true, 
        "filter_outliers_dict": {
            "filter_outliers": true, 
            "iterations": 1, 
            "std_devs": 2
        }, 
        "fit": "Average", 
        "fn": 111, 
        "include_baseline_error": false, 
        "iterations": 1, 
        "n": 120, 
        "std_devs": 2, 
        "value": -0.150725167966238
    }, 
    "L1": {
        "error": 0.001941098588040275, 
        "filter_outliers": true, 
        "filter_outliers_dict": {
            "filter_outliers": true, 
            "iterations": 1, 
            "std_devs": 2
        }, 
        "fit": "Average", 
        "fn": 114, 
        "include_baseline_error": false, 
        "iterations": 1, 
        "n": 120, 
        "std_devs": 2, 
        "value": -0.0194562391234764
    }, 
    "L2": {
        "error": 0.0038965903532521603, 
        "filter_outliers": true, 
        "filter_outliers_dict": {
            "filter_outliers": true, 
            "iterations": 1, 
            "std_devs": 2
        }, 
        "fit": "Average", 
        "fn": 115, 
        "include_baseline_error": false, 
        "iterations": 1, 
        "n": 120, 
        "std_devs": 2, 
        "value": -0.010860596365376335
    }
}