{
    "AX": {
        "error": 0.003867793586479992, 
        "filter_outliers": true, 
        "filter_outliers_dict": {
            "filter_outliers": true, 
            "iterations": 1, 
            "std_devs": 2
        }, 
        "fit": "Average", 
        "fn": 114, 
        "include_baseline_error": false, 
        "iterations": 1, 
        "n": 120, 
        "std_devs": 2, 
        "value": -0.030251680371931575
    }, 
    "CDD": {
        "error": 4.616419521607616e-06, 
        "filter_outliers": true, 
        "filter_outliers_dict": {
            "filter_outliers": true, 
            "iterations": 1, 
            "std_devs": 10
        }, 
        "fit": "Average", 
        "fn": 120, 
        "include_baseline_error": false, 
        "iterations": 1, 
        "n": 120, 
        "std_devs": 10, 
        "value": 1.9752500035489597e-05
    }, 
    "H1": {
        "error": 0.002912301188353163, 
        "filter_outliers": true, 
        "filter_outliers_dict": {
            "filter_outliers": true, 
            "iterations": 1, 
            "std_devs": 2
        }, 
        "fit": "Average", 
        "fn": 116, 
        "include_baseline_error": false, 
        "iterations": 1, 
        "n": 120, 
        "std_devs": 2, 
        "value": -0.044694312940480124
    }, 
    "H2": {
        "error": 0.005303462896079483, 
        "filter_outliers": true, 
        "filter_outliers_dict": {
            "filter_outliers": true, 
            "iterations": 1, 
            "std_devs": 2
        }, 
        "fit": "Average", 
        "fn": 113, 
        "include_baseline_error": false, 
        "iterations": 1, 
        "n": 120, 
        "std_devs": 2, 
        "value": -0.13043533690352058
    }, 
    "L1": {
        "error": 0.002017507030748274, 
        "filter_outliers": true, 
        "filter_outliers_dict": {
            "filter_outliers": true, 
            "iterations": 1, 
            "std_devs": 2
        }, 
        "fit": "Average", 
        "fn": 113, 
        "include_baseline_error": false, 
        "iterations": 1, 
        "n": 120, 
        "std_devs": 2, 
        "value": -0.012223198765732217
    }, 
    "L2": {
        "error": 0.004511955939270508, 
        "filter_outliers": true, 
        "filter_outliers_dict": {
            "filter_outliers": true, 
            "iterations": 1, 
            "std_devs": 2
        }, 
        "fit": "Average", 
        "fn": 115, 
        "include_baseline_error": false, 
        "iterations": 1, 
        "n": 120, 
        "std_devs": 2, 
        "value": -0.021032426348360986
    }
}