{
    "AX": {
        "error": 0.005379472101341216, 
        "filter_outliers": true, 
        "filter_outliers_dict": {
            "filter_outliers": true, 
            "iterations": 1, 
            "std_devs": 2
        }, 
        "fit": "Average", 
        "fn": 116, 
        "include_baseline_error": false, 
        "iterations": 1, 
        "n": 120, 
        "std_devs": 2, 
        "value": -0.005662810414425371
    }, 
    "CDD": {
        "error": 9.348639905904841e-05, 
        "filter_outliers": true, 
        "filter_outliers_dict": {
            "filter_outliers": true, 
            "iterations": 1, 
            "std_devs": 10
        }, 
        "fit": "Average", 
        "fn": 120, 
        "include_baseline_error": false, 
        "iterations": 1, 
        "n": 120, 
        "std_devs": 10, 
        "value": 0.005728226929204538
    }, 
    "H1": {
        "error": 0.016211271002150366, 
        "filter_outliers": true, 
        "filter_outliers_dict": {
            "filter_outliers": true, 
            "iterations": 1, 
            "std_devs": 2
        }, 
        "fit": "Average", 
        "fn": 117, 
        "include_baseline_error": false, 
        "iterations": 1, 
        "n": 120, 
        "std_devs": 2, 
        "value": 0.5635503073278655
    }, 
    "H2": {
        "error": 0.01724675029172409, 
        "filter_outliers": true, 
        "filter_outliers_dict": {
            "filter_outliers": true, 
            "iterations": 1, 
            "std_devs": 2
        }, 
        "fit": "Average", 
        "fn": 116, 
        "include_baseline_error": false, 
        "iterations": 1, 
        "n": 120, 
        "std_devs": 2, 
        "value": -0.23942466454122793
    }, 
    "L1": {
        "error": 0.002230536553639405, 
        "filter_outliers": true, 
        "filter_outliers_dict": {
            "filter_outliers": true, 
            "iterations": 1, 
            "std_devs": 2
        }, 
        "fit": "Average", 
        "fn": 117, 
        "include_baseline_error": false, 
        "iterations": 1, 
        "n": 120, 
        "std_devs": 2, 
        "value": 0.00010405592849223405
    }, 
    "L2": {
        "error": 0.004471419125880891, 
        "filter_outliers": true, 
        "filter_outliers_dict": {
            "filter_outliers": true, 
            "iterations": 1, 
            "std_devs": 2
        }, 
        "fit": "Average", 
        "fn": 115, 
        "include_baseline_error": false, 
        "iterations": 1, 
        "n": 120, 
        "std_devs": 2, 
        "value": -0.011240613176588617
    }
}