{
    "AX": {
        "error": 0.004220551403884796, 
        "filter_outliers_dict": {
            "filter_outliers": true, 
            "iterations": 1, 
            "std_devs": 2
        }, 
        "fit": "average", 
        "value": -0.028475242954598495
    }, 
    "CDD": {
        "error": 5.345377456460952e-06, 
        "filter_outliers_dict": {
            "filter_outliers": true, 
            "iterations": 1, 
            "std_devs": 10
        }, 
        "fit": "average", 
        "value": 2.0987030515188125e-05
    }, 
    "H1": {
        "error": 0.00366520658418673, 
        "filter_outliers_dict": {
            "filter_outliers": true, 
            "iterations": 1, 
            "std_devs": 2
        }, 
        "fit": "average", 
        "value": -0.03684158122782457
    }, 
    "H2": {
        "error": 0.006508146085688895, 
        "filter_outliers_dict": {
            "filter_outliers": true, 
            "iterations": 1, 
            "std_devs": 2
        }, 
        "fit": "average", 
        "value": -0.16066955589165352
    }, 
    "L1": {
        "error": 0.0016159113109035987, 
        "filter_outliers_dict": {
            "filter_outliers": true, 
            "iterations": 1, 
            "std_devs": 2
        }, 
        "fit": "average", 
        "value": -0.02315476955405958
    }, 
    "L2": {
        "error": 0.004269331525158729, 
        "filter_outliers_dict": {
            "filter_outliers": true, 
            "iterations": 1, 
            "std_devs": 2
        }, 
        "fit": "average", 
        "value": -0.018074332476124524
    }
}