{
    "AX": {
        "error": 0.004872511517605363, 
        "filter_outliers_dict": {
            "filter_outliers": true, 
            "iterations": 1, 
            "std_devs": 2
        }, 
        "fit": "average", 
        "value": -0.03911478970238892
    }, 
    "CDD": {
        "error": 4.435312250452431e-06, 
        "filter_outliers_dict": {
            "filter_outliers": true, 
            "iterations": 1, 
            "std_devs": 10
        }, 
        "fit": "average", 
        "value": 1.4814374471613516e-05
    }, 
    "H1": {
        "error": 0.0037123095942690155, 
        "filter_outliers_dict": {
            "filter_outliers": true, 
            "iterations": 1, 
            "std_devs": 2
        }, 
        "fit": "average", 
        "value": -0.035856523970435004
    }, 
    "H2": {
        "error": 0.00546169349367762, 
        "filter_outliers_dict": {
            "filter_outliers": true, 
            "iterations": 1, 
            "std_devs": 2
        }, 
        "fit": "average", 
        "value": -0.15131139841299387
    }, 
    "L1": {
        "error": 0.0019155721182233657, 
        "filter_outliers_dict": {
            "filter_outliers": true, 
            "iterations": 1, 
            "std_devs": 2
        }, 
        "fit": "average", 
        "value": -0.017753479442831507
    }, 
    "L2": {
        "error": 0.004286636609336116, 
        "filter_outliers_dict": {
            "filter_outliers": true, 
            "iterations": 1, 
            "std_devs": 2
        }, 
        "fit": "average", 
        "value": -0.01402036954536688
    }
}